hpc_scheduler/__init__.py
hpc_scheduler/scheduler.py
hpc_scheduler-0.1.2.dist-info/AUTHORS.rst
hpc_scheduler-0.1.2.dist-info/LICENSE
hpc_scheduler-0.1.2.dist-info/METADATA
hpc_scheduler-0.1.2.dist-info/WHEEL
hpc_scheduler-0.1.2.dist-info/top_level.txt
hpc_scheduler-0.1.2.dist-info/RECORD
