Metadata-Version: 2.1
Name: hpc-scheduler
Version: 0.1.2
Summary: Python code to interact with an HPC scheduler.
Home-page: https://github.com/euro-cordex/hpc_scheduler
Author: Lars Buntemeyer
Author-email: lars.buntemeyer@hzg.de
License: MIT license
Keywords: scheduler
Platform: UNKNOWN
Classifier: Development Status :: 2 - Pre-Alpha
Classifier: Intended Audience :: Developers
Classifier: License :: OSI Approved :: MIT License
Classifier: Natural Language :: English
Classifier: Programming Language :: Python :: 3
Classifier: Programming Language :: Python :: 3.5
Classifier: Programming Language :: Python :: 3.6
Classifier: Programming Language :: Python :: 3.7
Classifier: Programming Language :: Python :: 3.8
Requires-Python: >=3.5
Requires-Dist: configobj
